Metadata-Version: 1.0
Name: mlintro-distrib
Version: 0.1
Summary: Gaussian distributions
Home-page: UNKNOWN
Author: UNKNOWN
Author-email: isaac.gutierrez@msn.com
License: UNKNOWN
Platform: UNKNOWN
